{
  "timeline": [
    {
      "ora": "00:44",
      "score": 0,
      "classe": "ok"
    },
    {
      "ora": "01:43",
      "score": 0,
      "classe": "ok"
    },
    {
      "ora": "03:12",
      "score": 0,
      "classe": "ok"
    },
    {
      "ora": "06:47",
      "score": 0,
      "classe": "ok"
    },
    {
      "ora": "09:15",
      "score": 0,
      "classe": "ok"
    },
    {
      "ora": "11:10",
      "score": 1.222222222222222,
      "classe": "ok"
    },
    {
      "ora": "12:46",
      "score": 0,
      "classe": "ok"
    },
    {
      "ora": "13:58",
      "score": 4.646825396825396,
      "classe": "ok"
    },
    {
      "ora": "15:46",
      "score": 8.600255427841635,
      "classe": "warn"
    }
  ],
  "stazioni": {
    "ivreaandata": {
      "stats": {
        "total": 5,
        "delayedCount": 0,
        "avgDelay": 0,
        "maxDelay": 0,
        "soppressi": 0,
        "soppressiTrains": [],
        "delayedTrains": []
      },
      "error": null
    },
    "ivrearitorno": {
      "stats": {
        "total": 6,
        "delayedCount": 0,
        "avgDelay": 0,
        "maxDelay": 0,
        "soppressi": 0,
        "soppressiTrains": [],
        "delayedTrains": []
      },
      "error": null
    },
    "chivassoandata": {
      "stats": {
        "total": 29,
        "delayedCount": 1,
        "avgDelay": 20,
        "maxDelay": 20,
        "soppressi": 0,
        "soppressiTrains": [],
        "delayedTrains": [
          {
            "treno": "2028",
            "orario": "15:40",
            "luogo": "MILANO CENTRALE",
            "ritardo": 20
          }
        ]
      },
      "error": null
    },
    "chivassoritorno": {
      "stats": {
        "total": 29,
        "delayedCount": 1,
        "avgDelay": 20,
        "maxDelay": 20,
        "soppressi": 0,
        "soppressiTrains": [],
        "delayedTrains": [
          {
            "treno": "2028",
            "orario": "15:42",
            "luogo": "TORINO PORTA NUOVA",
            "ritardo": 20
          }
        ]
      },
      "error": null
    },
    "torinoandata": {
      "stats": {
        "total": 9,
        "delayedCount": 1,
        "avgDelay": 20,
        "maxDelay": 20,
        "soppressi": 0,
        "soppressiTrains": [],
        "delayedTrains": [
          {
            "treno": "2028",
            "orario": "16:06",
            "luogo": "MILANO CENTRALE",
            "ritardo": 20
          }
        ]
      },
      "error": null
    },
    "torinoritorno": {
      "stats": {
        "total": 9,
        "delayedCount": 0,
        "avgDelay": 0,
        "maxDelay": 0,
        "soppressi": 0,
        "soppressiTrains": [],
        "delayedTrains": []
      },
      "error": null
    }
  },
  "dataLog": "11/07/2026",
  "lastUpdate": "11/07/2026, 15:46:52",
  "totalScore": 8.600255427841635,
  "verdettoAttuale": {
    "cls": "warn",
    "word": "VAI CON RISERVA",
    "sub": "Qualche accumulo di ritardo qua e là."
  }
}