{
  "timeline": [
    {
      "ora": "00:08",
      "score": 0,
      "classe": "ok"
    },
    {
      "ora": "01:52",
      "score": 0,
      "classe": "ok"
    },
    {
      "ora": "06:02",
      "score": 0,
      "classe": "ok"
    },
    {
      "ora": "10:12",
      "score": 1.75,
      "classe": "ok"
    },
    {
      "ora": "13:35",
      "score": 3.950617283950617,
      "classe": "ok"
    },
    {
      "ora": "18:28",
      "score": 5.13086913086913,
      "classe": "ok"
    },
    {
      "ora": "20:12",
      "score": 17.776315789473685,
      "classe": "danger"
    },
    {
      "ora": "22:07",
      "score": 0,
      "classe": "ok"
    }
  ],
  "stazioni": {
    "ivreaandata": {
      "stats": {
        "total": 1,
        "delayedCount": 0,
        "avgDelay": 0,
        "maxDelay": 0,
        "soppressi": 0,
        "soppressiTrains": [],
        "delayedTrains": []
      },
      "error": null
    },
    "ivrearitorno": {
      "stats": {
        "total": 0,
        "delayedCount": 0,
        "avgDelay": 0,
        "maxDelay": 0,
        "soppressi": 0,
        "soppressiTrains": [],
        "delayedTrains": []
      },
      "error": null
    },
    "chivassoandata": {
      "stats": {
        "total": 5,
        "delayedCount": 0,
        "avgDelay": 0,
        "maxDelay": 0,
        "soppressi": 0,
        "soppressiTrains": [],
        "delayedTrains": []
      },
      "error": null
    },
    "chivassoritorno": {
      "stats": {
        "total": 6,
        "delayedCount": 0,
        "avgDelay": 0,
        "maxDelay": 0,
        "soppressi": 0,
        "soppressiTrains": [],
        "delayedTrains": []
      },
      "error": null
    },
    "torinoandata": {
      "stats": {
        "total": 3,
        "delayedCount": 0,
        "avgDelay": 0,
        "maxDelay": 0,
        "soppressi": 0,
        "soppressiTrains": [],
        "delayedTrains": []
      },
      "error": null
    },
    "torinoritorno": {
      "stats": {
        "total": 1,
        "delayedCount": 0,
        "avgDelay": 0,
        "maxDelay": 0,
        "soppressi": 0,
        "soppressiTrains": [],
        "delayedTrains": []
      },
      "error": null
    }
  },
  "dataLog": "10/07/2026",
  "lastUpdate": "10/07/2026, 22:07:23",
  "totalScore": 0,
  "verdettoAttuale": {
    "cls": "ok",
    "word": "VAI TRANQUILLO",
    "sub": "Treni in linea con le aspettative."
  }
}