{
  "timeline": [
    {
      "ora": "00:39",
      "score": 0,
      "classe": "ok"
    },
    {
      "ora": "03:04",
      "score": 0,
      "classe": "ok"
    },
    {
      "ora": "06:34",
      "score": 0,
      "classe": "ok"
    },
    {
      "ora": "08:58",
      "score": 3.965242165242165,
      "classe": "ok"
    },
    {
      "ora": "11:13",
      "score": 0,
      "classe": "ok"
    },
    {
      "ora": "13:12",
      "score": 0,
      "classe": "ok"
    },
    {
      "ora": "14:53",
      "score": 2.5758377425044094,
      "classe": "ok"
    },
    {
      "ora": "17:00",
      "score": 1.4615384615384617,
      "classe": "ok"
    },
    {
      "ora": "18:53",
      "score": 10.38119288119288,
      "classe": "warn"
    }
  ],
  "stazioni": {
    "ivreaandata": {
      "stats": {
        "total": 6,
        "delayedCount": 0,
        "avgDelay": 0,
        "maxDelay": 0,
        "soppressi": 0,
        "soppressiTrains": [],
        "delayedTrains": []
      },
      "error": null
    },
    "ivrearitorno": {
      "stats": {
        "total": 3,
        "delayedCount": 0,
        "avgDelay": 0,
        "maxDelay": 0,
        "soppressi": 0,
        "soppressiTrains": [],
        "delayedTrains": []
      },
      "error": null
    },
    "chivassoandata": {
      "stats": {
        "total": 28,
        "delayedCount": 2,
        "avgDelay": 20,
        "maxDelay": 35,
        "soppressi": 0,
        "soppressiTrains": [],
        "delayedTrains": [
          {
            "treno": "2034",
            "orario": "18:40",
            "luogo": "MILANO CENTRALE",
            "ritardo": 35
          },
          {
            "treno": "11378",
            "orario": "19:20",
            "luogo": "NOVARA",
            "ritardo": 5
          }
        ]
      },
      "error": null
    },
    "chivassoritorno": {
      "stats": {
        "total": 27,
        "delayedCount": 3,
        "avgDelay": 16.666666666666668,
        "maxDelay": 35,
        "soppressi": 0,
        "soppressiTrains": [],
        "delayedTrains": [
          {
            "treno": "2034",
            "orario": "18:42",
            "luogo": "TORINO PORTA NUOVA",
            "ritardo": 35
          },
          {
            "treno": "2739",
            "orario": "18:52",
            "luogo": "IVREA",
            "ritardo": 10
          },
          {
            "treno": "11378",
            "orario": "19:23",
            "luogo": "IVREA",
            "ritardo": 5
          }
        ]
      },
      "error": null
    },
    "torinoandata": {
      "stats": {
        "total": 11,
        "delayedCount": 2,
        "avgDelay": 20,
        "maxDelay": 35,
        "soppressi": 0,
        "soppressiTrains": [],
        "delayedTrains": [
          {
            "treno": "2004",
            "orario": "18:50",
            "luogo": "MILANO PORTA GARIBALDI",
            "ritardo": 5
          },
          {
            "treno": "2034",
            "orario": "19:06",
            "luogo": "MILANO CENTRALE",
            "ritardo": 35
          }
        ]
      },
      "error": null
    },
    "torinoritorno": {
      "stats": {
        "total": 6,
        "delayedCount": 0,
        "avgDelay": 0,
        "maxDelay": 0,
        "soppressi": 0,
        "soppressiTrains": [],
        "delayedTrains": []
      },
      "error": null
    }
  },
  "dataLog": "14/07/2026",
  "lastUpdate": "14/07/2026, 18:53:56",
  "totalScore": 10.38119288119288,
  "verdettoAttuale": {
    "cls": "warn",
    "word": "VAI CON RISERVA",
    "sub": "Qualche accumulo di ritardo qua e là."
  }
}